odoo10_addon_account_invoice_payment_report-10.0.1.0.1-py3.8-nspkg.pth
odoo/addons/account_invoice_payment_report/README.rst
odoo/addons/account_invoice_payment_report/__init__.py
odoo/addons/account_invoice_payment_report/__manifest__.py
odoo/addons/account_invoice_payment_report/i18n/account_invoice_payment_report.pot
odoo/addons/account_invoice_payment_report/i18n/de.po
odoo/addons/account_invoice_payment_report/i18n/fr.po
odoo/addons/account_invoice_payment_report/models/__init__.py
odoo/addons/account_invoice_payment_report/models/account_invoice.py
odoo/addons/account_invoice_payment_report/readme/CONTRIBUTORS.rst
odoo/addons/account_invoice_payment_report/readme/DESCRIPTION.rst
odoo/addons/account_invoice_payment_report/static/description/icon.png
odoo/addons/account_invoice_payment_report/static/description/index.html
odoo/addons/account_invoice_payment_report/views/account_report.xml
odoo/addons/account_invoice_payment_report/views/report_invoice.xml
odoo10_addon_account_invoice_payment_report-10.0.1.0.1.dist-info/METADATA
odoo10_addon_account_invoice_payment_report-10.0.1.0.1.dist-info/WHEEL
odoo10_addon_account_invoice_payment_report-10.0.1.0.1.dist-info/namespace_packages.txt
odoo10_addon_account_invoice_payment_report-10.0.1.0.1.dist-info/top_level.txt
odoo10_addon_account_invoice_payment_report-10.0.1.0.1.dist-info/RECORD
